{
    "name": "parsegraph-checkglerror",
    "version": "1.4.3",
    "description": "checkglerror",
    "main": "dist/parsegraph-checkglerror.js",
    "types": "dist/parsegraph-checkglerror.d.ts",
    "repository": {
      "type": "git",
      "url": "git+ssh://git@github.com/parsegraph/checkglerror.git"
    },
    "author": "Rainback, Inc.",
    "license": "MIT",
    "bugs": {
      "url": "https://github.com/parsegraph/checkglerror/issues"
    },
    "homepage": "https://github.com/parsegraph/checkglerror#readme"
  }